sd_webui_all_in_one/__init__.py
sd_webui_all_in_one/cmd.py
sd_webui_all_in_one/colab_tools.py
sd_webui_all_in_one/config.py
sd_webui_all_in_one/downloader.py
sd_webui_all_in_one/env.py
sd_webui_all_in_one/env_manager.py
sd_webui_all_in_one/file_manager.py
sd_webui_all_in_one/git_warpper.py
sd_webui_all_in_one/kaggle_tools.py
sd_webui_all_in_one/logger.py
sd_webui_all_in_one/mirror_manager.py
sd_webui_all_in_one/pytorch_mirror.py
sd_webui_all_in_one/repo_manager.py
sd_webui_all_in_one/tunnel.py
sd_webui_all_in_one/utils.py
sd_webui_all_in_one/version.py
sd_webui_all_in_one/env_check/__init__.py
sd_webui_all_in_one/env_check/comfyui_env_analyze.py
sd_webui_all_in_one/env_check/fix_dependencies.py
sd_webui_all_in_one/env_check/fix_numpy.py
sd_webui_all_in_one/env_check/fix_torch.py
sd_webui_all_in_one/env_check/onnxruntime_gpu_check.py
sd_webui_all_in_one/env_check/sd_webui_extension_dependency_installer.py
sd_webui_all_in_one/manager/__init__.py
sd_webui_all_in_one/manager/base_manager.py
sd_webui_all_in_one/manager/comfyui_manager.py
sd_webui_all_in_one/manager/fooocus_manager.py
sd_webui_all_in_one/manager/invokeai_manager.py
sd_webui_all_in_one/manager/sd_scripts_manager.py
sd_webui_all_in_one/manager/sd_trainer_manager.py
sd_webui_all_in_one/manager/sd_webui_manager.py
sd_webui_all_in_one/optimize/__init__.py
sd_webui_all_in_one/optimize/cuda_malloc.py
sd_webui_all_in_one/optimize/tcmalloc.py
sd_webui_all_in_one/package_analyzer/__init__.py
sd_webui_all_in_one/package_analyzer/pkg_check.py
sd_webui_all_in_one/package_analyzer/py_ver_cmp.py
sd_webui_all_in_one/package_analyzer/py_whl_parse.py
sd_webui_all_in_one/package_analyzer/ver_cmp.py
sd_webui_all_in_one/sdaio_patcher/sdaio_initializer.py
sd_webui_all_in_one/sdaio_patcher/sitecustomize.py
sd_webui_all_in_one/sdaio_patcher/sdaio_patches/__init__.py
sd_webui_all_in_one/sdaio_patcher/sdaio_patches/uv_patch.py
sd_webui_all_in_one/sdaio_patcher/sdaio_utils/__init__.py
sd_webui_all_in_one-1.2.15.dist-info/licenses/LICENSE
sd_webui_all_in_one-1.2.15.dist-info/METADATA
sd_webui_all_in_one-1.2.15.dist-info/WHEEL
sd_webui_all_in_one-1.2.15.dist-info/top_level.txt
sd_webui_all_in_one-1.2.15.dist-info/RECORD
