Metadata-Version: 2.4
Name: sd-webui-all-in-one
Version: 1.2.15
Summary: 支持部署多个 WebUI 的部署工具
Author: licyk
License-Expression: GPL-3.0
Requires-Python: >=3.10
License-File: LICENSE
Dynamic: license-file
